{
  "annotations": {
    "list": [
      {
        "builtIn": 1,
        "datasource": {
          "type": "grafana",
          "uid": "-- Grafana --"
        },
        "enable": true,
        "hide": true,
        "iconColor": "rgba(0, 211, 255, 1)",
        "name": "Annotations & Alerts",
        "type": "dashboard"
      }
    ]
  },
  "description": "Real-time Azure IoT Fleet Monitoring Dashboard",
  "editable": true,
  "fiscalYearStartMonth": 0,
  "graphTooltip": 0,
  "links": [],
  "panels": [
    {
      "fieldConfig": {
        "defaults": {},
        "overrides": []
      },
      "gridPos": {
        "h": 5,
        "w": 15,
        "x": 1,
        "y": 0
      },
      "id": 29,
      "options": {
        "code": {
          "language": "plaintext",
          "showLineNumbers": false,
          "showMiniMap": false
        },
        "content": "<div style=\"text-align:center; padding:20px;\">\r\n\r\n<h1>🚗 EV Fleet Monitoring Platform</h1>\r\n\r\n<h3>Production-Inspired Azure Serverless IoT Architecture</h3>\r\n\r\n<p>\r\n<b>Version:</b> 1.0.0 &nbsp; | &nbsp;\r\n<b>Region:</b>  Germany West Central &nbsp; | &nbsp;\r\n<b>Status:</b> 🟢 LIVE\r\n</p>\r\n</div>",
        "mode": "markdown"
      },
      "pluginVersion": "12.4.3",
      "title": "",
      "type": "text"
    },
    {
      "datasource": {
        "type": "yesoreyeram-infinity-datasource",
        "uid": "cfrdh4ohmv400e"
      },
      "description": "Fleet Simulator operational status.",
      "fieldConfig": {
        "defaults": {
          "color": {
            "mode": "thresholds"
          },
          "mappings": [],
          "thresholds": {
            "mode": "absolute",
            "steps": [
              {
                "color": "light-green",
                "value": 0
              },
              {
                "color": "red",
                "value": 80
              }
            ]
          }
        },
        "overrides": []
      },
      "gridPos": {
        "h": 3,
        "w": 3,
        "x": 1,
        "y": 5
      },
      "id": 24,
      "options": {
        "colorMode": "value",
        "graphMode": "area",
        "justifyMode": "center",
        "orientation": "auto",
        "percentChangeColorMode": "standard",
        "reduceOptions": {
          "calcs": [
            "lastNotNull"
          ],
          "fields": "/^simulator_status$/",
          "values": false
        },
        "showPercentChange": false,
        "textMode": "auto",
        "wideLayout": true
      },
      "pluginVersion": "12.4.3",
      "targets": [
        {
          "columns": [],
          "datasource": {
            "type": "yesoreyeram-infinity-datasource",
            "uid": "cfrdh4ohmv400e"
          },
          "filters": [],
          "format": "table",
          "global_query_id": "",
          "parser": "backend",
          "refId": "A",
          "root_selector": "*",
          "source": "url",
          "type": "json",
          "uql": "parse-json",
          "url": "https://evfleet-function-dev-bff6azb0eqgpcycx.germanywestcentral-01.azurewebsites.net/api/dashboard/status",
          "url_options": {
            "data": "",
            "method": "GET"
          }
        }
      ],
      "title": "🟢 Simulator",
      "type": "stat"
    },
    {
      "datasource": {
        "type": "yesoreyeram-infinity-datasource",
        "uid": "cfrdh4ohmv400e"
      },
      "description": "MQTT Edge Gateway connectivity status.",
      "fieldConfig": {
        "defaults": {
          "color": {
            "mode": "thresholds"
          },
          "mappings": [],
          "thresholds": {
            "mode": "absolute",
            "steps": [
              {
                "color": "light-green",
                "value": 0
              },
              {
                "color": "red",
                "value": 80
              }
            ]
          }
        },
        "overrides": []
      },
      "gridPos": {
        "h": 3,
        "w": 3,
        "x": 4,
        "y": 5
      },
      "id": 28,
      "options": {
        "colorMode": "value",
        "graphMode": "area",
        "justifyMode": "auto",
        "orientation": "auto",
        "percentChangeColorMode": "standard",
        "reduceOptions": {
          "calcs": [
            "lastNotNull"
          ],
          "fields": "/^edge_gateway_status$/",
          "values": false
        },
        "showPercentChange": false,
        "textMode": "auto",
        "wideLayout": true
      },
      "pluginVersion": "12.4.3",
      "targets": [
        {
          "columns": [],
          "datasource": {
            "type": "yesoreyeram-infinity-datasource",
            "uid": "cfrdh4ohmv400e"
          },
          "filters": [],
          "format": "table",
          "global_query_id": "",
          "parser": "backend",
          "refId": "A",
          "root_selector": "*",
          "source": "url",
          "type": "json",
          "uql": "parse-json",
          "url": "https://evfleet-function-dev-bff6azb0eqgpcycx.germanywestcentral-01.azurewebsites.net/api/dashboard/status",
          "url_options": {
            "data": "",
            "method": "GET"
          }
        }
      ],
      "title": "📡 Edge Gateway",
      "type": "stat"
    },
    {
      "datasource": {
        "type": "yesoreyeram-infinity-datasource",
        "uid": "cfrdh4ohmv400e"
      },
      "description": "Build Version",
      "fieldConfig": {
        "defaults": {
          "color": {
            "fixedColor": "super-light-blue",
            "mode": "fixed"
          },
          "mappings": [],
          "thresholds": {
            "mode": "absolute",
            "steps": [
              {
                "color": "blue",
                "value": 0
              },
              {
                "color": "red",
                "value": 80
              }
            ]
          },
          "unit": "dateTimeAsSystem"
        },
        "overrides": []
      },
      "gridPos": {
        "h": 3,
        "w": 3,
        "x": 7,
        "y": 5
      },
      "id": 25,
      "options": {
        "colorMode": "value",
        "graphMode": "area",
        "justifyMode": "auto",
        "orientation": "auto",
        "percentChangeColorMode": "standard",
        "reduceOptions": {
          "calcs": [
            "lastNotNull"
          ],
          "fields": "/^build_version$/",
          "values": false
        },
        "showPercentChange": false,
        "textMode": "auto",
        "wideLayout": true
      },
      "pluginVersion": "12.4.3",
      "targets": [
        {
          "columns": [],
          "datasource": {
            "type": "yesoreyeram-infinity-datasource",
            "uid": "cfrdh4ohmv400e"
          },
          "filters": [],
          "format": "table",
          "global_query_id": "",
          "parser": "backend",
          "refId": "A",
          "root_selector": "*",
          "source": "url",
          "type": "json",
          "uql": "parse-json",
          "url": "https://evfleet-function-dev-bff6azb0eqgpcycx.germanywestcentral-01.azurewebsites.net/api/dashboard/status",
          "url_options": {
            "data": "",
            "method": "GET"
          }
        }
      ],
      "title": "📦 Build Version",
      "type": "stat"
    },
    {
      "datasource": {
        "type": "yesoreyeram-infinity-datasource",
        "uid": "cfrdh4ohmv400e"
      },
      "description": "☁️ API Version",
      "fieldConfig": {
        "defaults": {
          "color": {
            "fixedColor": "super-light-blue",
            "mode": "fixed"
          },
          "mappings": [],
          "thresholds": {
            "mode": "absolute",
            "steps": [
              {
                "color": "blue",
                "value": 0
              },
              {
                "color": "red",
                "value": 80
              }
            ]
          }
        },
        "overrides": []
      },
      "gridPos": {
        "h": 3,
        "w": 3,
        "x": 10,
        "y": 5
      },
      "id": 26,
      "options": {
        "colorMode": "value",
        "graphMode": "area",
        "justifyMode": "auto",
        "orientation": "auto",
        "percentChangeColorMode": "standard",
        "reduceOptions": {
          "calcs": [
            "lastNotNull"
          ],
          "fields": "/^api_version$/",
          "values": false
        },
        "showPercentChange": false,
        "textMode": "auto",
        "wideLayout": true
      },
      "pluginVersion": "12.4.3",
      "targets": [
        {
          "columns": [],
          "datasource": {
            "type": "yesoreyeram-infinity-datasource",
            "uid": "cfrdh4ohmv400e"
          },
          "filters": [],
          "format": "table",
          "global_query_id": "",
          "parser": "backend",
          "refId": "A",
          "root_selector": "*",
          "source": "url",
          "type": "json",
          "uql": "parse-json",
          "url": "https://evfleet-function-dev-bff6azb0eqgpcycx.germanywestcentral-01.azurewebsites.net/api/dashboard/status",
          "url_options": {
            "data": "",
            "method": "GET"
          }
        }
      ],
      "title": "☁️ API Version",
      "type": "stat"
    },
    {
      "datasource": {
        "type": "yesoreyeram-infinity-datasource",
        "uid": "cfrdh4ohmv400e"
      },
      "description": "Last updated",
      "fieldConfig": {
        "defaults": {
          "color": {
            "mode": "thresholds"
          },
          "mappings": [],
          "thresholds": {
            "mode": "absolute",
            "steps": [
              {
                "color": "green",
                "value": 0
              },
              {
                "color": "light-green",
                "value": 0
              },
              {
                "color": "#EAB839",
                "value": 15
              },
              {
                "color": "light-red",
                "value": 30
              }
            ]
          },
          "unit": "dateTimeFromNow"
        },
        "overrides": []
      },
      "gridPos": {
        "h": 3,
        "w": 3,
        "x": 13,
        "y": 5
      },
      "id": 27,
      "options": {
        "colorMode": "value",
        "graphMode": "area",
        "justifyMode": "center",
        "orientation": "auto",
        "percentChangeColorMode": "standard",
        "reduceOptions": {
          "calcs": [
            "lastNotNull"
          ],
          "fields": "/^last_update$/",
          "values": false
        },
        "showPercentChange": false,
        "textMode": "value",
        "wideLayout": true
      },
      "pluginVersion": "12.4.3",
      "targets": [
        {
          "columns": [],
          "datasource": {
            "type": "yesoreyeram-infinity-datasource",
            "uid": "cfrdh4ohmv400e"
          },
          "filters": [],
          "format": "table",
          "global_query_id": "",
          "parser": "backend",
          "refId": "A",
          "root_selector": "*",
          "source": "url",
          "type": "json",
          "uql": "parse-json",
          "url": "https://evfleet-function-dev-bff6azb0eqgpcycx.germanywestcentral-01.azurewebsites.net/api/dashboard/status",
          "url_options": {
            "data": "",
            "method": "GET"
          }
        }
      ],
      "title": "🕒 Last Update",
      "type": "stat"
    },
    {
      "datasource": {
        "type": "yesoreyeram-infinity-datasource",
        "uid": "cfrdh4ohmv400e"
      },
      "description": "Number of connected vehicles.",
      "fieldConfig": {
        "defaults": {
          "color": {
            "mode": "thresholds"
          },
          "mappings": [],
          "thresholds": {
            "mode": "absolute",
            "steps": [
              {
                "color": "green",
                "value": 0
              },
              {
                "color": "red",
                "value": 80
              }
            ]
          }
        },
        "overrides": []
      },
      "gridPos": {
        "h": 3,
        "w": 3,
        "x": 3,
        "y": 8
      },
      "id": 1,
      "options": {
        "colorMode": "value",
        "graphMode": "area",
        "justifyMode": "auto",
        "orientation": "auto",
        "percentChangeColorMode": "standard",
        "reduceOptions": {
          "calcs": [
            "lastNotNull"
          ],
          "fields": "",
          "values": false
        },
        "showPercentChange": false,
        "textMode": "value",
        "wideLayout": true
      },
      "pluginVersion": "12.4.3",
      "targets": [
        {
          "columns": [],
          "datasource": {
            "type": "yesoreyeram-infinity-datasource",
            "uid": "cfrdh4ohmv400e"
          },
          "filters": [],
          "format": "table",
          "global_query_id": "",
          "parser": "backend",
          "refId": "A",
          "root_selector": "vehicles_online",
          "source": "url",
          "type": "json",
          "url": "https://evfleet-function-dev-bff6azb0eqgpcycx.germanywestcentral-01.azurewebsites.net/api/dashboard/summary",
          "url_options": {
            "data": "",
            "method": "GET"
          }
        }
      ],
      "title": "🚗 Online",
      "type": "stat"
    },
    {
      "datasource": {
        "type": "yesoreyeram-infinity-datasource",
        "uid": "cfrdh4ohmv400e"
      },
      "description": "Azure Region",
      "fieldConfig": {
        "defaults": {
          "color": {
            "fixedColor": "super-light-blue",
            "mode": "fixed"
          },
          "mappings": [],
          "thresholds": {
            "mode": "absolute",
            "steps": [
              {
                "color": "blue",
                "value": 0
              },
              {
                "color": "red",
                "value": 80
              }
            ]
          },
          "unit": "dateTimeAsSystem"
        },
        "overrides": []
      },
      "gridPos": {
        "h": 3,
        "w": 3,
        "x": 7,
        "y": 8
      },
      "id": 30,
      "options": {
        "colorMode": "value",
        "graphMode": "area",
        "justifyMode": "auto",
        "orientation": "auto",
        "percentChangeColorMode": "standard",
        "reduceOptions": {
          "calcs": [
            "lastNotNull"
          ],
          "fields": "/^azure_region$/",
          "values": false
        },
        "showPercentChange": false,
        "textMode": "auto",
        "wideLayout": true
      },
      "pluginVersion": "12.4.3",
      "targets": [
        {
          "columns": [],
          "datasource": {
            "type": "yesoreyeram-infinity-datasource",
            "uid": "cfrdh4ohmv400e"
          },
          "filters": [],
          "format": "table",
          "global_query_id": "",
          "parser": "backend",
          "refId": "A",
          "root_selector": "*",
          "source": "url",
          "type": "json",
          "uql": "parse-json",
          "url": "https://evfleet-function-dev-bff6azb0eqgpcycx.germanywestcentral-01.azurewebsites.net/api/dashboard/status",
          "url_options": {
            "data": "",
            "method": "GET"
          }
        }
      ],
      "title": " ☁ Azure Region",
      "type": "stat"
    },
    {
      "datasource": {
        "type": "yesoreyeram-infinity-datasource",
        "uid": "cfrdh4ohmv400e"
      },
      "description": "Vehicle actually driving",
      "fieldConfig": {
        "defaults": {
          "color": {
            "mode": "thresholds"
          },
          "mappings": [],
          "thresholds": {
            "mode": "absolute",
            "steps": [
              {
                "color": "green",
                "value": 0
              },
              {
                "color": "red",
                "value": 80
              }
            ]
          }
        },
        "overrides": []
      },
      "gridPos": {
        "h": 3,
        "w": 3,
        "x": 11,
        "y": 8
      },
      "id": 5,
      "options": {
        "colorMode": "value",
        "graphMode": "area",
        "justifyMode": "auto",
        "orientation": "auto",
        "percentChangeColorMode": "standard",
        "reduceOptions": {
          "calcs": [
            "lastNotNull"
          ],
          "fields": "",
          "values": false
        },
        "showPercentChange": false,
        "textMode": "value",
        "wideLayout": true
      },
      "pluginVersion": "12.4.3",
      "targets": [
        {
          "columns": [],
          "datasource": {
            "type": "yesoreyeram-infinity-datasource",
            "uid": "cfrdh4ohmv400e"
          },
          "filters": [],
          "format": "table",
          "global_query_id": "",
          "parser": "backend",
          "refId": "A",
          "root_selector": "driving",
          "source": "url",
          "type": "json",
          "url": "https://evfleet-function-dev-bff6azb0eqgpcycx.germanywestcentral-01.azurewebsites.net/api/dashboard/summary",
          "url_options": {
            "data": "",
            "method": "GET"
          }
        }
      ],
      "title": "🛣 Driving",
      "type": "stat"
    },
    {
      "datasource": {
        "type": "yesoreyeram-infinity-datasource",
        "uid": "cfrdh4ohmv400e"
      },
      "description": "Overall health score of the EV fleet based on battery status, temperature and active faults",
      "fieldConfig": {
        "defaults": {
          "color": {
            "mode": "thresholds"
          },
          "mappings": [],
          "max": 100,
          "thresholds": {
            "mode": "absolute",
            "steps": [
              {
                "color": "green",
                "value": 0
              },
              {
                "color": "red",
                "value": 0
              },
              {
                "color": "#EAB839",
                "value": 60
              },
              {
                "color": "green",
                "value": 90
              }
            ]
          },
          "unit": "percent"
        },
        "overrides": []
      },
      "gridPos": {
        "h": 3,
        "w": 3,
        "x": 1,
        "y": 11
      },
      "id": 11,
      "options": {
        "colorMode": "value",
        "graphMode": "area",
        "justifyMode": "center",
        "orientation": "auto",
        "percentChangeColorMode": "standard",
        "reduceOptions": {
          "calcs": [
            "lastNotNull"
          ],
          "fields": "",
          "values": false
        },
        "showPercentChange": false,
        "textMode": "value",
        "wideLayout": true
      },
      "pluginVersion": "12.4.3",
      "targets": [
        {
          "columns": [],
          "datasource": {
            "type": "yesoreyeram-infinity-datasource",
            "uid": "cfrdh4ohmv400e"
          },
          "filters": [],
          "format": "table",
          "global_query_id": "",
          "parser": "backend",
          "refId": "A",
          "root_selector": "fleet_health",
          "source": "url",
          "type": "json",
          "url": "https://evfleet-function-dev-bff6azb0eqgpcycx.germanywestcentral-01.azurewebsites.net/api/dashboard/summary",
          "url_options": {
            "data": "",
            "method": "GET"
          }
        }
      ],
      "title": "❤️ Health Score",
      "type": "stat"
    },
    {
      "datasource": {
        "type": "yesoreyeram-infinity-datasource",
        "uid": "cfrdh4ohmv400e"
      },
      "description": "Vehicles currently reporting active faults.",
      "fieldConfig": {
        "defaults": {
          "color": {
            "mode": "thresholds"
          },
          "mappings": [],
          "max": 100,
          "min": 0,
          "thresholds": {
            "mode": "absolute",
            "steps": [
              {
                "color": "green",
                "value": 0
              },
              {
                "color": "green",
                "value": 0
              },
              {
                "color": "#EAB839",
                "value": 1
              },
              {
                "color": "red",
                "value": 3
              }
            ]
          }
        },
        "overrides": []
      },
      "gridPos": {
        "h": 3,
        "w": 3,
        "x": 4,
        "y": 11
      },
      "id": 7,
      "options": {
        "colorMode": "value",
        "graphMode": "area",
        "justifyMode": "auto",
        "orientation": "auto",
        "percentChangeColorMode": "standard",
        "reduceOptions": {
          "calcs": [
            "lastNotNull"
          ],
          "fields": "",
          "values": false
        },
        "showPercentChange": false,
        "textMode": "value",
        "wideLayout": true
      },
      "pluginVersion": "12.4.3",
      "targets": [
        {
          "columns": [],
          "datasource": {
            "type": "yesoreyeram-infinity-datasource",
            "uid": "cfrdh4ohmv400e"
          },
          "filters": [],
          "format": "table",
          "global_query_id": "",
          "parser": "backend",
          "refId": "A",
          "root_selector": "fault",
          "source": "url",
          "type": "json",
          "url": "https://evfleet-function-dev-bff6azb0eqgpcycx.germanywestcentral-01.azurewebsites.net/api/dashboard/summary",
          "url_options": {
            "data": "",
            "method": "GET"
          }
        }
      ],
      "title": "⚠️ Faults",
      "type": "stat"
    },
    {
      "datasource": {
        "type": "yesoreyeram-infinity-datasource",
        "uid": "cfrdh4ohmv400e"
      },
      "description": "Total number of telemetry documents stored in Cosmos DB.",
      "fieldConfig": {
        "defaults": {
          "color": {
            "fixedColor": "super-light-blue",
            "mode": "fixed"
          },
          "mappings": [],
          "thresholds": {
            "mode": "absolute",
            "steps": [
              {
                "color": "green",
                "value": 0
              },
              {
                "color": "red",
                "value": 80
              }
            ]
          }
        },
        "overrides": []
      },
      "gridPos": {
        "h": 3,
        "w": 3,
        "x": 7,
        "y": 11
      },
      "id": 32,
      "options": {
        "colorMode": "value",
        "graphMode": "area",
        "justifyMode": "auto",
        "orientation": "auto",
        "percentChangeColorMode": "standard",
        "reduceOptions": {
          "calcs": [
            "lastNotNull"
          ],
          "fields": "/^messages_processed$/",
          "values": false
        },
        "showPercentChange": false,
        "textMode": "auto",
        "wideLayout": true
      },
      "pluginVersion": "12.4.3",
      "targets": [
        {
          "columns": [],
          "datasource": {
            "type": "yesoreyeram-infinity-datasource",
            "uid": "cfrdh4ohmv400e"
          },
          "filters": [],
          "format": "table",
          "global_query_id": "",
          "parser": "backend",
          "refId": "A",
          "root_selector": "",
          "source": "url",
          "type": "json",
          "url": "https://evfleet-function-dev-bff6azb0eqgpcycx.germanywestcentral-01.azurewebsites.net/api/dashboard/summary",
          "url_options": {
            "data": "",
            "method": "GET"
          }
        }
      ],
      "title": "📧 Messages Processed",
      "type": "stat"
    },
    {
      "datasource": {
        "type": "yesoreyeram-infinity-datasource",
        "uid": "cfrdh4ohmv400e"
      },
      "description": "Number of parked vehicles",
      "fieldConfig": {
        "defaults": {
          "color": {
            "mode": "thresholds"
          },
          "fieldMinMax": false,
          "mappings": [],
          "thresholds": {
            "mode": "absolute",
            "steps": [
              {
                "color": "green",
                "value": 0
              },
              {
                "color": "red",
                "value": 80
              }
            ]
          },
          "unit": "none"
        },
        "overrides": []
      },
      "gridPos": {
        "h": 3,
        "w": 3,
        "x": 10,
        "y": 11
      },
      "id": 6,
      "options": {
        "colorMode": "value",
        "graphMode": "area",
        "justifyMode": "auto",
        "orientation": "auto",
        "percentChangeColorMode": "standard",
        "reduceOptions": {
          "calcs": [
            "lastNotNull"
          ],
          "fields": "",
          "values": false
        },
        "showPercentChange": false,
        "textMode": "value",
        "wideLayout": true
      },
      "pluginVersion": "12.4.3",
      "targets": [
        {
          "columns": [],
          "datasource": {
            "type": "yesoreyeram-infinity-datasource",
            "uid": "cfrdh4ohmv400e"
          },
          "filters": [],
          "format": "table",
          "global_query_id": "",
          "parser": "backend",
          "refId": "A",
          "root_selector": "parked",
          "source": "url",
          "type": "json",
          "url": "https://evfleet-function-dev-bff6azb0eqgpcycx.germanywestcentral-01.azurewebsites.net/api/dashboard/summary",
          "url_options": {
            "data": "",
            "method": "GET"
          }
        }
      ],
      "title": "🅿 Parked",
      "type": "stat"
    },
    {
      "datasource": {
        "type": "yesoreyeram-infinity-datasource",
        "uid": "cfrdh4ohmv400e"
      },
      "description": "Vehiles in Charging state",
      "fieldConfig": {
        "defaults": {
          "color": {
            "mode": "thresholds"
          },
          "mappings": [],
          "max": 100,
          "min": 0,
          "thresholds": {
            "mode": "absolute",
            "steps": [
              {
                "color": "green",
                "value": 0
              },
              {
                "color": "super-light-blue",
                "value": 0
              },
              {
                "color": "light-blue",
                "value": 60
              },
              {
                "color": "dark-blue",
                "value": 80
              }
            ]
          }
        },
        "overrides": []
      },
      "gridPos": {
        "h": 3,
        "w": 3,
        "x": 13,
        "y": 11
      },
      "id": 4,
      "options": {
        "colorMode": "value",
        "graphMode": "area",
        "justifyMode": "auto",
        "orientation": "auto",
        "percentChangeColorMode": "standard",
        "reduceOptions": {
          "calcs": [
            "lastNotNull"
          ],
          "fields": "",
          "values": false
        },
        "showPercentChange": false,
        "textMode": "value",
        "wideLayout": true
      },
      "pluginVersion": "12.4.3",
      "targets": [
        {
          "columns": [],
          "datasource": {
            "type": "yesoreyeram-infinity-datasource",
            "uid": "cfrdh4ohmv400e"
          },
          "filters": [],
          "format": "table",
          "global_query_id": "",
          "parser": "backend",
          "refId": "A",
          "root_selector": "charging",
          "source": "url",
          "type": "json",
          "url": "https://evfleet-function-dev-bff6azb0eqgpcycx.germanywestcentral-01.azurewebsites.net/api/dashboard/summary",
          "url_options": {
            "data": "",
            "method": "GET"
          }
        }
      ],
      "title": "⚡ Charging",
      "type": "stat"
    },
    {
      "datasource": {
        "type": "yesoreyeram-infinity-datasource",
        "uid": "cfrdh4ohmv400e"
      },
      "description": "Historical fleet telemetry evolution.",
      "fieldConfig": {
        "defaults": {
          "color": {
            "mode": "palette-classic"
          },
          "custom": {
            "axisBorderShow": false,
            "axisCenteredZero": false,
            "axisColorMode": "text",
            "axisLabel": "",
            "axisPlacement": "auto",
            "barAlignment": 0,
            "barWidthFactor": 0.6,
            "drawStyle": "line",
            "fillOpacity": 15,
            "gradientMode": "none",
            "hideFrom": {
              "legend": false,
              "tooltip": false,
              "viz": false
            },
            "insertNulls": false,
            "lineInterpolation": "linear",
            "lineWidth": 3,
            "pointSize": 5,
            "scaleDistribution": {
              "type": "linear"
            },
            "showPoints": "auto",
            "showValues": false,
            "spanNulls": false,
            "stacking": {
              "group": "A",
              "mode": "none"
            },
            "thresholdsStyle": {
              "mode": "off"
            }
          },
          "mappings": [],
          "thresholds": {
            "mode": "absolute",
            "steps": [
              {
                "color": "green",
                "value": 0
              },
              {
                "color": "red",
                "value": 80
              }
            ]
          },
          "unit": "celsius"
        },
        "overrides": [
          {
            "matcher": {
              "id": "byName",
              "options": "Average SOC"
            },
            "properties": [
              {
                "id": "color",
                "value": {
                  "fixedColor": "green",
                  "mode": "fixed"
                }
              },
              {
                "id": "unit",
                "value": "percent"
              },
              {
                "id": "custom.lineWidth",
                "value": 3
              },
              {
                "id": "custom.axisPlacement",
                "value": "left"
              },
              {
                "id": "custom.fillOpacity",
                "value": 10
              },
              {
                "id": "displayName",
                "value": "Average SOC"
              }
            ]
          },
          {
            "matcher": {
              "id": "byName",
              "options": "Average Temperature"
            },
            "properties": [
              {
                "id": "color",
                "value": {
                  "fixedColor": "orange",
                  "mode": "fixed"
                }
              },
              {
                "id": "unit",
                "value": "celsius"
              },
              {
                "id": "custom.lineWidth",
                "value": 2
              },
              {
                "id": "custom.axisPlacement",
                "value": "right"
              },
              {
                "id": "custom.fillOpacity",
                "value": 10
              }
            ]
          }
        ]
      },
      "gridPos": {
        "h": 8,
        "w": 15,
        "x": 1,
        "y": 14
      },
      "id": 18,
      "options": {
        "legend": {
          "calcs": [],
          "displayMode": "list",
          "placement": "bottom",
          "showLegend": true
        },
        "tooltip": {
          "hideZeros": false,
          "mode": "single",
          "sort": "none"
        }
      },
      "pluginVersion": "12.4.3",
      "targets": [
        {
          "columns": [
            {
              "selector": "timestamp",
              "text": "Time",
              "type": "timestamp"
            },
            {
              "selector": "average_soc",
              "text": "Average SOC",
              "type": "number"
            },
            {
              "selector": "average_temperature",
              "text": "Average Temperature",
              "type": "number"
            }
          ],
          "datasource": {
            "type": "yesoreyeram-infinity-datasource",
            "uid": "cfrdh4ohmv400e"
          },
          "filters": [],
          "format": "timeseries",
          "global_query_id": "",
          "parser": "backend",
          "refId": "A",
          "root_selector": "",
          "source": "url",
          "type": "json",
          "uql": "parse-json\r\n| project timestamp, average_soc, average_temperature",
          "url": "https://evfleet-function-dev-bff6azb0eqgpcycx.germanywestcentral-01.azurewebsites.net/api/dashboard/trends",
          "url_options": {
            "data": "",
            "method": "GET"
          }
        }
      ],
      "title": "📈 Fleet Telemetry Trends",
      "type": "timeseries"
    },
    {
      "datasource": {
        "type": "yesoreyeram-infinity-datasource",
        "uid": "cfrdh4ohmv400e"
      },
      "description": "Average battery State of Charge across the fleet.",
      "fieldConfig": {
        "defaults": {
          "color": {
            "mode": "thresholds"
          },
          "mappings": [],
          "thresholds": {
            "mode": "absolute",
            "steps": [
              {
                "color": "green",
                "value": 0
              },
              {
                "color": "red",
                "value": 0
              },
              {
                "color": "#EAB839",
                "value": 20
              },
              {
                "color": "green",
                "value": 50
              }
            ]
          },
          "unit": "percent"
        },
        "overrides": []
      },
      "gridPos": {
        "h": 6,
        "w": 5,
        "x": 1,
        "y": 22
      },
      "id": 12,
      "options": {
        "minVizHeight": 75,
        "minVizWidth": 75,
        "orientation": "auto",
        "reduceOptions": {
          "calcs": [
            "lastNotNull"
          ],
          "fields": "",
          "values": false
        },
        "showThresholdLabels": false,
        "showThresholdMarkers": true,
        "sizing": "auto"
      },
      "pluginVersion": "12.4.3",
      "targets": [
        {
          "columns": [],
          "datasource": {
            "type": "yesoreyeram-infinity-datasource",
            "uid": "cfrdh4ohmv400e"
          },
          "filters": [],
          "format": "table",
          "global_query_id": "",
          "parser": "backend",
          "refId": "A",
          "root_selector": "average_soc",
          "source": "url",
          "type": "json",
          "url": "https://evfleet-function-dev-bff6azb0eqgpcycx.germanywestcentral-01.azurewebsites.net/api/dashboard/summary",
          "url_options": {
            "data": "",
            "method": "GET"
          }
        }
      ],
      "title": "🔋 Average SOC",
      "type": "gauge"
    },
    {
      "datasource": {
        "type": "yesoreyeram-infinity-datasource",
        "uid": "cfrdh4ohmv400e"
      },
      "description": "Average currrent",
      "fieldConfig": {
        "defaults": {
          "color": {
            "mode": "thresholds"
          },
          "mappings": [],
          "thresholds": {
            "mode": "absolute",
            "steps": [
              {
                "color": "green",
                "value": 0
              }
            ]
          },
          "unit": "amp"
        },
        "overrides": []
      },
      "gridPos": {
        "h": 3,
        "w": 3,
        "x": 7,
        "y": 22
      },
      "id": 10,
      "options": {
        "colorMode": "value",
        "graphMode": "area",
        "justifyMode": "auto",
        "orientation": "auto",
        "percentChangeColorMode": "standard",
        "reduceOptions": {
          "calcs": [
            "lastNotNull"
          ],
          "fields": "",
          "values": false
        },
        "showPercentChange": false,
        "textMode": "value",
        "wideLayout": true
      },
      "pluginVersion": "12.4.3",
      "targets": [
        {
          "columns": [],
          "datasource": {
            "type": "yesoreyeram-infinity-datasource",
            "uid": "cfrdh4ohmv400e"
          },
          "filters": [],
          "format": "table",
          "global_query_id": "",
          "parser": "backend",
          "refId": "A",
          "root_selector": "average_current",
          "source": "url",
          "type": "json",
          "url": "https://evfleet-function-dev-bff6azb0eqgpcycx.germanywestcentral-01.azurewebsites.net/api/dashboard/summary",
          "url_options": {
            "data": "",
            "method": "GET"
          }
        }
      ],
      "title": "⚡ Current",
      "type": "stat"
    },
    {
      "datasource": {
        "type": "yesoreyeram-infinity-datasource",
        "uid": "cfrdh4ohmv400e"
      },
      "description": "Average battery temperature.",
      "fieldConfig": {
        "defaults": {
          "color": {
            "mode": "thresholds"
          },
          "mappings": [],
          "max": 100,
          "min": 0,
          "thresholds": {
            "mode": "absolute",
            "steps": [
              {
                "color": "green",
                "value": 0
              },
              {
                "color": "green",
                "value": 45
              },
              {
                "color": "#EAB839",
                "value": 60
              },
              {
                "color": "red",
                "value": 80
              }
            ]
          },
          "unit": "celsius"
        },
        "overrides": []
      },
      "gridPos": {
        "h": 6,
        "w": 5,
        "x": 11,
        "y": 22
      },
      "id": 13,
      "options": {
        "minVizHeight": 75,
        "minVizWidth": 75,
        "orientation": "auto",
        "reduceOptions": {
          "calcs": [
            "lastNotNull"
          ],
          "fields": "",
          "values": false
        },
        "showThresholdLabels": false,
        "showThresholdMarkers": true,
        "sizing": "auto"
      },
      "pluginVersion": "12.4.3",
      "targets": [
        {
          "columns": [],
          "datasource": {
            "type": "yesoreyeram-infinity-datasource",
            "uid": "cfrdh4ohmv400e"
          },
          "filters": [],
          "format": "table",
          "global_query_id": "",
          "parser": "backend",
          "refId": "A",
          "root_selector": "average_temperature",
          "source": "url",
          "type": "json",
          "url": "https://evfleet-function-dev-bff6azb0eqgpcycx.germanywestcentral-01.azurewebsites.net/api/dashboard/summary",
          "url_options": {
            "data": "",
            "method": "GET"
          }
        }
      ],
      "title": "🌡 Temperature",
      "type": "gauge"
    },
    {
      "datasource": {
        "type": "yesoreyeram-infinity-datasource",
        "uid": "cfrdh4ohmv400e"
      },
      "description": "Battery Voltage",
      "fieldConfig": {
        "defaults": {
          "color": {
            "mode": "thresholds"
          },
          "fieldMinMax": false,
          "mappings": [],
          "thresholds": {
            "mode": "absolute",
            "steps": [
              {
                "color": "green",
                "value": 0
              },
              {
                "color": "red",
                "value": 80
              }
            ]
          },
          "unit": "volt"
        },
        "overrides": []
      },
      "gridPos": {
        "h": 3,
        "w": 3,
        "x": 7,
        "y": 25
      },
      "id": 9,
      "options": {
        "colorMode": "value",
        "graphMode": "area",
        "justifyMode": "auto",
        "orientation": "auto",
        "percentChangeColorMode": "standard",
        "reduceOptions": {
          "calcs": [
            "lastNotNull"
          ],
          "fields": "",
          "values": false
        },
        "showPercentChange": false,
        "textMode": "value",
        "wideLayout": true
      },
      "pluginVersion": "12.4.3",
      "targets": [
        {
          "columns": [],
          "datasource": {
            "type": "yesoreyeram-infinity-datasource",
            "uid": "cfrdh4ohmv400e"
          },
          "filters": [],
          "format": "table",
          "global_query_id": "",
          "parser": "backend",
          "refId": "A",
          "root_selector": "average_voltage",
          "source": "url",
          "type": "json",
          "url": "https://evfleet-function-dev-bff6azb0eqgpcycx.germanywestcentral-01.azurewebsites.net/api/dashboard/summary",
          "url_options": {
            "data": "",
            "method": "GET"
          }
        }
      ],
      "title": "🔌 Voltage",
      "type": "stat"
    },
    {
      "datasource": {
        "type": "yesoreyeram-infinity-datasource",
        "uid": "cfrdh4ohmv400e"
      },
      "description": "Fleet Vehicles",
      "fieldConfig": {
        "defaults": {
          "color": {
            "mode": "thresholds"
          },
          "custom": {
            "align": "auto",
            "cellOptions": {
              "type": "auto"
            },
            "footer": {
              "reducers": []
            },
            "inspect": false
          },
          "mappings": [],
          "thresholds": {
            "mode": "absolute",
            "steps": [
              {
                "color": "green",
                "value": 0
              },
              {
                "color": "red",
                "value": 80
              }
            ]
          }
        },
        "overrides": [
          {
            "matcher": {
              "id": "byName",
              "options": "Fault"
            },
            "properties": [
              {
                "id": "custom.width",
                "value": 215
              }
            ]
          }
        ]
      },
      "gridPos": {
        "h": 8,
        "w": 15,
        "x": 1,
        "y": 28
      },
      "id": 17,
      "options": {
        "cellHeight": "sm",
        "showHeader": true,
        "sortBy": [
          {
            "desc": false,
            "displayName": "Vehicle"
          }
        ]
      },
      "pluginVersion": "12.4.3",
      "targets": [
        {
          "columns": [
            {
              "selector": "vehicle",
              "text": "Vehicle",
              "type": "string"
            },
            {
              "selector": "state",
              "text": "State",
              "type": "string"
            },
            {
              "selector": "fault",
              "text": "Fault",
              "type": "string"
            },
            {
              "selector": "soc",
              "text": "SOC",
              "type": "number"
            },
            {
              "selector": "temperature",
              "text": "Temperature (°C)",
              "type": "number"
            },
            {
              "selector": "voltage",
              "text": "Voltage (V)",
              "type": "number"
            },
            {
              "selector": "current",
              "text": "Current (A)",
              "type": "number"
            }
          ],
          "datasource": {
            "type": "yesoreyeram-infinity-datasource",
            "uid": "cfrdh4ohmv400e"
          },
          "filters": [],
          "format": "table",
          "global_query_id": "",
          "parser": "backend",
          "refId": "A",
          "root_selector": "",
          "source": "url",
          "type": "json",
          "url": "https://evfleet-function-dev-bff6azb0eqgpcycx.germanywestcentral-01.azurewebsites.net/api/dashboard/vehicles",
          "url_options": {
            "data": "",
            "method": "GET"
          }
        }
      ],
      "title": "🚙 Fleet Vehicles",
      "transformations": [
        {
          "id": "organize",
          "options": {
            "excludeByName": {},
            "includeByName": {},
            "indexByName": {
              "Current (A)": 5,
              "Fault": 2,
              "SOC": 3,
              "State": 1,
              "Temperature (°C)": 4,
              "Vehicle": 0,
              "Voltage (V)": 6
            },
            "renameByName": {}
          }
        }
      ],
      "type": "table"
    }
  ],
  "preload": false,
  "refresh": "",
  "schemaVersion": 42,
  "tags": [],
  "templating": {
    "list": []
  },
  "time": {
    "from": "2026-07-21T00:08:13.421Z",
    "to": "2026-07-21T03:08:39.671Z"
  },
  "timepicker": {},
  "timezone": "browser",
  "title": "🚗 EV Fleet Monitoring Platform",
  "uid": "ibb2v6t",
  "version": 183,
  "weekStart": ""
}